setup.py
koto/__init__.py
koto/__main__.py
koto/db_methods.py
koto/gmail_methods.py
koto/koto.py
koto.egg-info/PKG-INFO
koto.egg-info/SOURCES.txt
koto.egg-info/dependency_links.txt
koto.egg-info/entry_points.txt
koto.egg-info/not-zip-safe
koto.egg-info/requires.txt
koto.egg-info/top_level.txt